odoo/addons/sequence_reset_period/README.rst
odoo/addons/sequence_reset_period/__init__.py
odoo/addons/sequence_reset_period/__manifest__.py
odoo/addons/sequence_reset_period/i18n/es.po
odoo/addons/sequence_reset_period/i18n/hr.po
odoo/addons/sequence_reset_period/i18n/pt.po
odoo/addons/sequence_reset_period/i18n/sequence_reset_period.pot
odoo/addons/sequence_reset_period/models/__init__.py
odoo/addons/sequence_reset_period/models/ir_sequence.py
odoo/addons/sequence_reset_period/readme/CONTRIBUTORS.rst
odoo/addons/sequence_reset_period/readme/DESCRIPTION.rst
odoo/addons/sequence_reset_period/readme/USAGE.rst
odoo/addons/sequence_reset_period/static/description/icon.png
odoo/addons/sequence_reset_period/static/description/index.html
odoo/addons/sequence_reset_period/tests/__init__.py
odoo/addons/sequence_reset_period/tests/test_period.py
odoo/addons/sequence_reset_period/views/sequence_views.xml
odoo12_addon_sequence_reset_period-12.0.1.0.0.99.dev10.dist-info/METADATA
odoo12_addon_sequence_reset_period-12.0.1.0.0.99.dev10.dist-info/WHEEL
odoo12_addon_sequence_reset_period-12.0.1.0.0.99.dev10.dist-info/top_level.txt
odoo12_addon_sequence_reset_period-12.0.1.0.0.99.dev10.dist-info/RECORD
